dana/__init__.py
dana/__main__.py
dana/dana_config.json
dana/__init__/__init__.py
dana/__init__/init_config.py
dana/__init__/init_environment.py
dana/__init__/init_integrations.py
dana/__init__/init_libs.py
dana/__init__/init_logging.py
dana/__init__/init_modules.py
dana/__init__/init_resources.py
dana/__init__/init_runtime.py
dana/agent/__init__.py
dana/agent/agent_instance.py
dana/agent/general_solver.py
dana/api/__init__.py
dana/api/client/__init__.py
dana/api/client/client.py
dana/api/core/__init__.py
dana/api/core/cli_migrations.py
dana/api/core/database.py
dana/api/core/exceptions.py
dana/api/core/migrations.py
dana/api/core/models.py
dana/api/core/schemas.py
dana/api/routers/__init__.py
dana/api/routers/agent_generator_na.py
dana/api/routers/agent_test.py
dana/api/routers/agents.py
dana/api/routers/api.py
dana/api/routers/chat.py
dana/api/routers/conversations.py
dana/api/routers/documents.py
dana/api/routers/domain_knowledge.py
dana/api/routers/extract_documents.py
dana/api/routers/main.py
dana/api/routers/poet.py
dana/api/routers/smart_chat.py
dana/api/routers/smart_chat_v2.py
dana/api/routers/topics.py
dana/api/server/__init__.py
dana/api/server/__main__.py
dana/api/server/server.py
dana/api/server/services.py
dana/api/server/assets/prebuilt_agents.json
dana/api/server/assets/jordan_financial_analyst/common.na
dana/api/server/assets/jordan_financial_analyst/knowledge.na
dana/api/server/assets/jordan_financial_analyst/main.na
dana/api/server/assets/jordan_financial_analyst/methods.na
dana/api/server/assets/jordan_financial_analyst/tools.na
dana/api/server/assets/jordan_financial_analyst/workflow.na
dana/api/server/assets/jordan_financial_stmt_analyst/common.na
dana/api/server/assets/jordan_financial_stmt_analyst/knowledge.na
dana/api/server/assets/jordan_financial_stmt_analyst/main.na
dana/api/server/assets/jordan_financial_stmt_analyst/methods.na
dana/api/server/assets/jordan_financial_stmt_analyst/tools.na
dana-0.25.9.4.dist-info/licenses/LICENSE.md
dana-0.25.9.4.dist-info/METADATA
dana-0.25.9.4.dist-info/WHEEL
dana-0.25.9.4.dist-info/entry_points.txt
dana-0.25.9.4.dist-info/top_level.txt
dana-0.25.9.4.dist-info/RECORD
