Metadata-Version: 2.4
Name: dana
Version: 0.25.9.4
Summary: Dana programming language for Domain-Aware Neurosymbolic Agents
Author-email: Christopher Nguyen <ctn@aitomatic.com>
Requires-Python: >=3.12
License-File: LICENSE.md
Requires-Dist: google-cloud-aiplatform
Requires-Dist: aisuite[anthropic,azure,groq,huggingface,ollama,openai]>=0.1.11
Requires-Dist: httpx>=0.27.0
Requires-Dist: mcp
Requires-Dist: llm-code-executor
Requires-Dist: llama-index
Requires-Dist: openai>=1.55.3
Requires-Dist: lark
Requires-Dist: pandas
Requires-Dist: matplotlib
Requires-Dist: seaborn
Requires-Dist: sqlalchemy
Requires-Dist: aiohttp
Requires-Dist: aioconsole
Requires-Dist: websockets
Requires-Dist: python-dotenv
Requires-Dist: pyyaml
Requires-Dist: structlog
Requires-Dist: prompt-toolkit
Requires-Dist: pygments
Requires-Dist: playwright
Requires-Dist: fastapi
Requires-Dist: uvicorn
Requires-Dist: pytest
Requires-Dist: pytest-asyncio
Requires-Dist: pytest-mock
Requires-Dist: lsprotocol
Requires-Dist: pygls
Requires-Dist: python-a2a>=0.5.9
Requires-Dist: tqdm
Requires-Dist: aicapture
Requires-Dist: python-lsp-server[all]>=1.13.0
Requires-Dist: pyright>=1.1.403
Requires-Dist: jedi>=0.19.2
Requires-Dist: llama-index-embeddings-openai>=0.3.1
Requires-Dist: llama-index-llms-cohere>=0.5.0
Requires-Dist: llama-index-vector-stores-duckdb>=0.4.6
Requires-Dist: llama-index-vector-stores-postgres>=0.5.5
Provides-Extra: dev
Requires-Dist: ruff; extra == "dev"
Requires-Dist: pylint; extra == "dev"
Requires-Dist: mypy; extra == "dev"
Requires-Dist: pre-commit; extra == "dev"
Requires-Dist: pytest-cov; extra == "dev"
Requires-Dist: build; extra == "dev"
Requires-Dist: twine; extra == "dev"
Provides-Extra: docs
Requires-Dist: mkdocs; extra == "docs"
Requires-Dist: mkdocs-material; extra == "docs"
Requires-Dist: mkdocs-mermaid2-plugin; extra == "docs"
Requires-Dist: mkdocs-section-index; extra == "docs"
Requires-Dist: mkdocstrings; extra == "docs"
Requires-Dist: mkdocstrings-python; extra == "docs"
Requires-Dist: mkdocs-git-revision-date-localized-plugin; extra == "docs"
Requires-Dist: pymdown-extensions[extra]; extra == "docs"
Requires-Dist: mkdocs-gen-files; extra == "docs"
Requires-Dist: mkdocs-literate-nav; extra == "docs"
Requires-Dist: mkdocs-htmlproofer-plugin; extra == "docs"
Requires-Dist: linkcheckmd; extra == "docs"
Requires-Dist: doc8; extra == "docs"
Requires-Dist: mkdocs-redirects; extra == "docs"
Requires-Dist: mkdocs-awesome-nav; extra == "docs"
Requires-Dist: mkdocs-print-site-plugin; extra == "docs"
Requires-Dist: mkdocs-include-markdown-plugin; extra == "docs"
Requires-Dist: mkdocs-macros-plugin; extra == "docs"
Requires-Dist: mkdocs-table-reader-plugin; extra == "docs"
Dynamic: license-file
